date_reclass/__init__.py
date_reclass/main/__init__.py
date_reclass/main/cast.py
date_reclass/main/is_json.py
json_datetime_util/__init__.py
json_datetime_util/main/__init__.py
json_datetime_util/main/is_json.py
json_datetime_util/main/jsondatetime.py
tests/__init__.py
tests/cast_datetime__str_test.py
tests/datetime_to_json_test.py
tests/example_test.py
tests/is_json_test.py
date_reclass-0.0.4.dist-info/LICENSE
date_reclass-0.0.4.dist-info/METADATA
date_reclass-0.0.4.dist-info/WHEEL
date_reclass-0.0.4.dist-info/top_level.txt
date_reclass-0.0.4.dist-info/RECORD
