Metadata-Version: 2.1
Name: date-reclass
Version: 0.0.4
Summary: Convert data from str to datetime or datetime to str.
Home-page: https://github.com/nicholasmole/date_reclass
Author: Nicholas Mole
Author-email: nmole065@gmail.com
License: UNKNOWN
Platform: UNKNOWN
Classifier: Programming Language :: Python :: 3
Classifier: License :: OSI Approved :: MIT License
Classifier: Operating System :: OS Independent
Requires-Python: >=3.6
